purescripto/__init__.py
purescripto/configure.py
purescripto/configure_consts.py
purescripto/installer.py
purescripto/pspy.py
purescripto/purescript_loader.py
purescripto/rts.py
purescripto/template_setup.py
purescripto/topdown.py
purescripto/utilities.py
purescripto/version.py
purescripto/workaround.py
purescripto-0.8.9.dist-info/LICENSE
purescripto-0.8.9.dist-info/METADATA
purescripto-0.8.9.dist-info/WHEEL
purescripto-0.8.9.dist-info/entry_points.txt
purescripto-0.8.9.dist-info/top_level.txt
purescripto-0.8.9.dist-info/RECORD
