Metadata-Version: 2.1
Name: purescripto
Version: 0.8.9
Summary: UNKNOWN
Home-page: https://github.com/purescript-python/purescripto
Author: thautawarm
Author-email: twshere@outlook.com
License: mit
Platform: any
Classifier: Programming Language :: Python :: 3.5
Classifier: Programming Language :: Python :: 3.6
Classifier: Programming Language :: Python :: 3.7
Classifier: Programming Language :: Python :: 3.8
Classifier: Programming Language :: Python :: Implementation :: CPython
Requires-Python: >=3.5
Requires-Dist: painless-import-extension
Requires-Dist: pysexpr (<=0.6,>=0.5)
Requires-Dist: wisepy2 (>=1.1.1)
Requires-Dist: gitpython
Requires-Dist: requests
